dungeon_driver/__init__.py
dungeon_driver/main.py
dungeon_driver/spell_surge_generator.py
dungeondriver-0.1.dist-info/METADATA
dungeondriver-0.1.dist-info/WHEEL
dungeondriver-0.1.dist-info/top_level.txt
dungeondriver-0.1.dist-info/RECORD
